plot_memory_usage/__init__.py
plot_memory_usage/plot_memory_usage_core.py
plot_memory_usage/utils.py
plot_memory_usage-0.0.1.dist-info/LICENSE
plot_memory_usage-0.0.1.dist-info/METADATA
plot_memory_usage-0.0.1.dist-info/WHEEL
plot_memory_usage-0.0.1.dist-info/entry_points.txt
plot_memory_usage-0.0.1.dist-info/top_level.txt
plot_memory_usage-0.0.1.dist-info/RECORD
