Metadata-Version: 2.1
Name: plot-memory-usage
Version: 0.0.1
Summary: Create a live plot of the CPU or GPU memory usage of your system over time
Home-page: https://github.com/tylerlum/plot_memory_usage
Author: Tyler Lum
Author-email: tylergwlum@gmail.com
License: UNKNOWN
Keywords: python,plot,memory,usage,cpu,gpu
Platform: UNKNOWN
Classifier: Intended Audience :: Developers
Classifier: Operating System :: OS Independent
Classifier: Programming Language :: Python :: 3
License-File: LICENSE
Requires-Dist: live-plotter
Requires-Dist: tyro
Requires-Dist: GPUtil
Requires-Dist: psutil
